MALRULES/MALRULES_analysis.py
MALRULES/__init__.py
MALRULES/hash_utils.py
MALRULES-0.1.dist-info/LICENSE
MALRULES-0.1.dist-info/METADATA
MALRULES-0.1.dist-info/WHEEL
MALRULES-0.1.dist-info/top_level.txt
MALRULES-0.1.dist-info/RECORD
